pydc/__init__.py
pydc/factory.py
pydc/pydc.py
pydc-0.1.0.dist-info/DESCRIPTION.rst
pydc-0.1.0.dist-info/METADATA
pydc-0.1.0.dist-info/RECORD
pydc-0.1.0.dist-info/WHEEL
pydc-0.1.0.dist-info/metadata.json
pydc-0.1.0.dist-info/top_level.txt
