Metadata-Version: 2.0
Name: pydc
Version: 0.1.0
Summary: Python library for generating Dublin Core XML
Home-page: UNKNOWN
Author: Sean Mosely
Author-email: sean.mosely@gmail.com
License: MIT
Download-URL: https://github.com/NLNZDigitalPreservation/pydc/archive/v0.1.0.tar.gz
Platform: UNKNOWN
Requires-Dist: lxml (==3.6.4)
